getpaid/__init__.py
getpaid/admin.py
getpaid/apps.py
getpaid/backends/__init__.py
getpaid/backends/dummy/__init__.py
getpaid/backends/dummy/apps.py
getpaid/backends/dummy/processor.py
getpaid/backends/dummy/templates/getpaid_dummy/payment_post_form.html
getpaid/backends/dummy/urls.py
getpaid/backends/dummy/views.py
getpaid/exceptions.py
getpaid/forms.py
getpaid/migrations/0001_initial.py
getpaid/migrations/0002_auto_20200417_2107.py
getpaid/migrations/__init__.py
getpaid/models.py
getpaid/post_forms.py
getpaid/processor.py
getpaid/registry.py
getpaid/status.py
getpaid/templatetags/__init__.py
getpaid/templatetags/getpaid.py
getpaid/types.py
getpaid/urls.py
getpaid/utils.py
getpaid/validators.py
getpaid/views.py
django_getpaid-2.2.2.dist-info/LICENSE
django_getpaid-2.2.2.dist-info/WHEEL
django_getpaid-2.2.2.dist-info/METADATA
django_getpaid-2.2.2.dist-info/RECORD
