Metadata-Version: 2.1
Name: django-getpaid
Version: 2.2.2
Summary: Multi-broker payment processor for Django.
Home-page: https://github.com/django-getpaid/django-getpaid
License: MIT
Author: Dominik Kozaczko
Author-email: dominik@kozaczko.info
Requires-Python: >=3.6.2,<4.0.0
Classifier: Development Status :: 4 - Beta
Classifier: Framework :: Django
Classifier: Framework :: Django :: 2.2
Classifier: Framework :: Django :: 3.1
Classifier: Framework :: Django :: 3.2
Classifier: License :: OSI Approved :: MIT License
Classifier: Programming Language :: Python :: 3
Classifier: Programming Language :: Python :: 3.7
Classifier: Programming Language :: Python :: 3.8
Classifier: Programming Language :: Python :: 3.9
Classifier: Topic :: Office/Business :: Financial
Classifier: Topic :: Office/Business :: Financial :: Point-Of-Sale
Provides-Extra: docs
Provides-Extra: graph
Provides-Extra: test
Requires-Dist: asgiref (>=3.3.4,<4.0.0); extra == "test"
Requires-Dist: codecov (>=2.1.11,<3.0.0); extra == "test"
Requires-Dist: coverage (>=5.5,<6.0); extra == "test"
Requires-Dist: django-fsm (>=2.7.1,<3.0.0)
Requires-Dist: django-model-utils (>=4.1.1,<5.0.0)
Requires-Dist: graphviz (>=0.13.2,<0.14.0); extra == "graph"
Requires-Dist: importlib-metadata (>=1.0,<2.0); python_version < "3.8"
Requires-Dist: pendulum (>=2.1.2,<3.0.0)
Requires-Dist: pytest (>=6.2.4,<7.0.0); extra == "test"
Requires-Dist: pytest-cov (>=2.12.1,<3.0.0); extra == "test"
Requires-Dist: pytest-django (>=4.3.0,<5.0.0); extra == "test"
Requires-Dist: pytest-factoryboy (>=2.1.0,<3.0.0); extra == "test"
Requires-Dist: requests (>=2.25.1,<3.0.0); extra == "test"
Requires-Dist: requests-mock (>=1.9.3,<2.0.0); extra == "test"
Requires-Dist: sphinx (>=3,<4); extra == "docs"
Requires-Dist: sphinx-rtd-theme (>=0.4.3,<0.5.0); extra == "docs"
Requires-Dist: swapper (>=1.1.2,<2.0.0)
Requires-Dist: typing-extensions (>=3.10.0,<4.0.0)
Project-URL: Documentation, https://django-getpaid.readthedocs.io/
Project-URL: Repository, https://github.com/django-getpaid/django-getpaid
